osintr/__init__.py
osintr/main.py
osintr-0.4.3.dist-info/LICENSE
osintr-0.4.3.dist-info/METADATA
osintr-0.4.3.dist-info/WHEEL
osintr-0.4.3.dist-info/entry_points.txt
osintr-0.4.3.dist-info/top_level.txt
osintr-0.4.3.dist-info/RECORD
